asepyte/__init__.py
asepyte/aseprite.py
asepyte/header.py
asepyte-0.0.5.dist-info/LICENSE
asepyte-0.0.5.dist-info/METADATA
asepyte-0.0.5.dist-info/WHEEL
asepyte-0.0.5.dist-info/top_level.txt
asepyte-0.0.5.dist-info/RECORD
